{
  "rec_id": "0211",
  "trace_id": 112,
  "predictions": {
    "1.1": 0,
    "1.2": 0,
    "1.3": 0,
    "1.4": 0,
    "1.5": 0,
    "2.1": 0,
    "2.2": 0,
    "2.3": 0,
    "2.4": 0,
    "2.6": 0,
    "3.1": 0,
    "3.2": 1,
    "3.3": 0
  },
  "raw_response": "@@\nA. The agents successfully identified the correct diagnosis, but the process was somewhat redundant. The Code Executor essentially provided the entire solution, and the Problem Solver didn't contribute significantly beyond confirming the result. The Verifier simply reiterated the Code Executor's analysis without adding substantial value. There's a lack of true collaboration and verification beyond confirmation.\nB. yes\nC.\n1.1 no\n1.2 no\n1.3 no\n1.4 no\n1.5 no\n2.1 no\n2.2 no\n2.3 no\n2.4 no\n2.6 no\n3.1 no\n3.2 yes\n3.3 no\n@@"
}