{
  "rec_id": "0199",
  "trace_id": 94,
  "predictions": {
    "1.1": 0,
    "1.2": 0,
    "1.3": 0,
    "1.4": 0,
    "1.5": 0,
    "2.1": 0,
    "2.2": 0,
    "2.3": 0,
    "2.4": 0,
    "2.6": 0,
    "3.1": 0,
    "3.2": 0,
    "3.3": 0
  },
  "raw_response": "@@\nA. The agents correctly identify the impact of a Japanese recession on US net exports, the dollar, and the yen. However, the interaction feels somewhat redundant, with each agent restating the same conclusions. The code executor simply confirms the problem solver's analysis with a trivial Python script. There's a lack of deeper investigation or alternative perspectives. The conversation also feels a bit forced, with explicit prompts for the next speaker.\nB. yes\nC.\n1.1 no\n1.2 no\n1.3 no\n1.4 no\n1.5 no\n2.1 no\n2.2 no\n2.3 no\n2.4 no\n2.6 no\n3.1 no\n3.2 no\n3.3 no\n@@"
}