{
  "rec_id": "0270",
  "trace_id": 44,
  "predictions": {
    "1.1": 0,
    "1.2": 0,
    "1.3": 1,
    "1.4": 0,
    "1.5": 1,
    "2.1": 0,
    "2.2": 0,
    "2.3": 0,
    "2.4": 0,
    "2.6": 0,
    "3.1": 0,
    "3.2": 0,
    "3.3": 0
  },
  "raw_response": "@@\nA. The agent is stuck in a loop, repeatedly providing the same answer (n=55) despite the mathproxyagent indicating it's incorrect and requesting a new approach. The agent is failing to explore alternative solution strategies or recognize that its current approach is not working. This demonstrates a lack of adaptability and problem-solving skills. The agent also repeats the same reasoning and code multiple times without making any meaningful progress.\nB. no\nC.\n1.1 no\n1.2 no\n1.3 yes\n1.4 no\n1.5 yes\n2.1 no\n2.2 no\n2.3 no\n2.4 no\n2.6 no\n3.1 no\n3.2 no\n3.3 no\n@@"
}