{
  "rec_id": "0280",
  "trace_id": 62,
  "predictions": {
    "1.1": 0,
    "1.2": 0,
    "1.3": 0,
    "1.4": 0,
    "1.5": 0,
    "2.1": 0,
    "2.2": 0,
    "2.3": 0,
    "2.4": 0,
    "2.6": 1,
    "3.1": 0,
    "3.2": 0,
    "3.3": 0
  },
  "raw_response": "A. The primary issue is the mathproxyagent providing incorrect solutions for 'y' and consequently 'x'. The initial setup and reasoning are sound, but the Python code execution yields incorrect results, which the assistant then accepts and presents as the final answer. This indicates a failure in verifying the computational results. There's also a lack of critical evaluation of the solutions obtained from the code. The agent doesn't question why the solutions are what they are or if they make sense in the context of the original problem.\n\nB. no\nC.\n1.1 no\n1.2 no\n1.3 no\n1.4 no\n1.5 no\n2.1 no\n2.2 no\n2.3 no\n2.4 no\n2.6 yes\n3.1 no\n3.2 no\n3.3 no"
}