{
  "rec_id": "0344",
  "trace_id": 142,
  "predictions": {
    "1.1": 0,
    "1.2": 0,
    "1.3": 0,
    "1.4": 0,
    "1.5": 0,
    "2.1": 0,
    "2.2": 0,
    "2.3": 0,
    "2.4": 0,
    "2.6": 1,
    "3.1": 0,
    "3.2": 0,
    "3.3": 0
  },
  "raw_response": "@@\nA. The trace shows several issues. The initial attempt to solve the problem using sympy resulted in an IndexError, indicating a problem with the code or the input to the solver. The assistant then attempted to correct the code and rerun the calculation, but the result (3.105) is incorrect. The final answer provided by the assistant is 37, but it's not clear if this is based on a correct calculation or a guess. There's a lot of back and forth without a clear path to a correct solution. The assistant also repeats the explanation of the approach multiple times. There's also a potential Action-Reasoning Mismatch as the initial reasoning seems sound, but the implementation leads to an error.\nB. no\nC.\n1.1 no\n1.2 no\n1.3 no\n1.4 no\n1.5 no\n2.1 no\n2.2 no\n2.3 no\n2.4 no\n2.6 yes\n3.1 no\n3.2 no\n3.3 no\n@@"
}