{
  "rec_id": "0203",
  "trace_id": 100,
  "predictions": {
    "1.1": 0,
    "1.2": 0,
    "1.3": 1,
    "1.4": 0,
    "1.5": 0,
    "2.1": 0,
    "2.2": 0,
    "2.3": 1,
    "2.4": 0,
    "2.6": 1,
    "3.1": 1,
    "3.2": 1,
    "3.3": 0
  },
  "raw_response": "A. The trace exhibits several issues, including task derailment, ignoring other agents' input, step repetition, and premature termination. Specifically, agents sometimes repeat the same thought or information, fail to acknowledge valid concerns raised by other agents (like needing more information to solve a problem), and prematurely end tasks without proper resolution. There are also instances of disobeying task specifications and action-reasoning mismatches.\n\nB. no\n\nC. \n1.1 no\n1.2 no\n1.3 yes \n1.4 no\n1.5 no\n2.1 no\n2.2 no\n2.3 yes\n2.4 no\n2.6 yes\n3.1 yes\n3.2 yes\n3.3 no\n"
}