{
  "rec_id": "0197",
  "trace_id": 92,
  "predictions": {
    "1.1": 1,
    "1.2": 0,
    "1.3": 1,
    "1.4": 1,
    "1.5": 1,
    "2.1": 0,
    "2.2": 1,
    "2.3": 1,
    "2.4": 0,
    "2.6": 1,
    "3.1": 0,
    "3.2": 1,
    "3.3": 1
  },
  "raw_response": "### Analysis of the Trace\n\n#### A. Freeform Text Summary of the Problems with the Inefficiencies or Failure Modes in the Trace:\nThe trace exhibits several inefficiencies and failure modes. The agents involved in the task do not effectively collaborate, leading to redundant steps, incomplete verification, and a lack of clarity in task specifications. The conversation history is lost, and the agents fail to ask for necessary clarifications, resulting in a suboptimal solution. Additionally, there is a mismatch between the reasoning and the actions taken, and the agents do not properly verify the outputs, leading to potential errors in the final solution.\n\n#### B. Whether the Task is Successfully Completed or Not:\n**no**\n\n#### C. Whether You Encounter Any of the Failure Modes or Inefficiencies:\n1.1 **Disobey Task Specification**: **yes**\n   - The agents do not fully adhere to the task specifications, leading to incomplete or incorrect outputs.\n\n1.2 **Disobey Role Specification**: **no**\n   - There is no evidence that agents are failing to adhere to their defined roles.\n\n1.3 **Step Repetition**: **yes**\n   - The agents repeat steps unnecessarily, such as re-evaluating the same neurotransmitters multiple times.\n\n1.4 **Loss of Conversation History**: **yes**\n   - The conversation history is lost, leading to redundant discussions and a lack of context.\n\n1.5 **Unaware of Termination Conditions**: **yes**\n   - The agents continue the conversation without recognizing when to terminate, leading to unnecessary steps.\n\n2.1 **Conversation Reset**: **no**\n   - There is no evidence of an unexpected or unwarranted restarting of the dialogue.\n\n2.2 **Fail to Ask for Clarification**: **yes**\n   - The agents do not ask for clarifications when faced with unclear or incomplete data, leading to incorrect assumptions.\n\n2.3 **Task Derailment**: **yes**\n   - The agents deviate from the intended objective, leading to irrelevant or unproductive actions.\n\n2.4 **Information Withholding**: **no**\n   - There is no evidence that critical information is withheld from other agents.\n\n2.6 **Action-Reasoning Mismatch**: **yes**\n   - There is a discrepancy between the logical discussion and the actual actions taken, leading to incorrect outputs.\n\n3.1 **Premature Termination**: **no**\n   - The task is not terminated prematurely; instead, it continues unnecessarily.\n\n3.2 **Weak Verification**: **yes**\n   - The verification mechanisms are weak, leading to incomplete or incorrect validation of the outputs.\n\n3.3 **No or Incorrect Verification**: **yes**\n   - There is no proper checking or confirmation of task outcomes, allowing errors to propagate undetected.\n\n### Detailed Examples of Failure Modes:\n\n1. **Disobey Task Specification**:\n   - The agents do not fully adhere to the task specifications, leading to incomplete or incorrect outputs. For example, the agents do not systematically evaluate all neurotransmitters and their roles in fatigue development.\n\n2. **Step Repetition**:\n   - The agents repeat steps unnecessarily, such as re-evaluating the same neurotransmitters multiple times. This redundancy wastes resources and time.\n\n3. **Loss of Conversation History**:\n   - The conversation history is lost, leading to redundant discussions and a lack of context. For example, the agents discuss the same neurotransmitters multiple times without referencing previous discussions.\n\n4. **Unaware of Termination Conditions**:\n   - The agents continue the conversation without recognizing when to terminate, leading to unnecessary steps. For example, the agents continue discussing neurotransmitters even after a conclusion has been reached.\n\n5. **Fail to Ask for Clarification**:\n   - The agents do not ask for clarifications when faced with unclear or incomplete data, leading to incorrect assumptions. For example, the agents do not seek additional information on the roles of specific neurotransmitters.\n\n6. **Task Derailment**:\n   - The agents deviate from the intended objective, leading to irrelevant or unproductive actions. For example, the agents spend time discussing neurotransmitters that are not directly relevant to fatigue development.\n\n7. **Action-Reasoning Mismatch**:\n   - There is a discrepancy between the logical discussion and the actual actions taken, leading to incorrect outputs. For example, the agents conclude that option D is the most influential but do not provide a clear rationale for this conclusion.\n\n8. **Weak Verification**:\n   - The verification mechanisms are weak, leading to incomplete or incorrect validation of the outputs. For example, the agents do not thoroughly verify the roles of neurotransmitters in fatigue development.\n\n9. **No or Incorrect Verification**:\n   - There is no proper checking or confirmation of task outcomes, allowing errors to propagate undetected. For example, the agents do not verify the final conclusion with additional evidence or research."
}